math_op/__init__.py
math_op-1.0.dist-info/METADATA
math_op-1.0.dist-info/WHEEL
math_op-1.0.dist-info/top_level.txt
math_op-1.0.dist-info/RECORD
